abbrey/__init__.py
abbrey/acronyms_ver0.1.csv
abbrey/decoder.py
abbrey-0.0.3.dist-info/LICENSE.txt
abbrey-0.0.3.dist-info/METADATA
abbrey-0.0.3.dist-info/WHEEL
abbrey-0.0.3.dist-info/top_level.txt
abbrey-0.0.3.dist-info/RECORD
