Metadata-Version: 2.1
Name: abbrey
Version: 0.0.3
Summary: Abbreviation decoder
Author: pdd
Author-email: dungphamdang99@gmail.com
License: MIT
Keywords: abbreviation
Classifier: Development Status :: 3 - Alpha
Classifier: Intended Audience :: Developers
Classifier: Topic :: Software Development :: Build Tools
Classifier: License :: OSI Approved :: MIT License
Classifier: Programming Language :: Python :: 3
License-File: LICENSE.txt
Requires-Dist: pandas
